circleci_flaky
